PyQtEnumConverter/PyQtEnumConverter.py
PyQtEnumConverter/__init__.py
PyQtEnumConverter-1.0.dist-info/METADATA
PyQtEnumConverter-1.0.dist-info/WHEEL
PyQtEnumConverter-1.0.dist-info/entry_points.txt
PyQtEnumConverter-1.0.dist-info/top_level.txt
PyQtEnumConverter-1.0.dist-info/RECORD
